[
  {
    "index":0,
    "timestamp":1777505995000,
    "hostname":"nid002240",
    "gpu_id":0,
    "nersc_ldms_dcgm_dram_active":0.0,
    "nersc_ldms_dcgm_fb_free":40441,
    "nersc_ldms_dcgm_fb_used":0,
    "nersc_ldms_dcgm_fp16_active":0,
    "nersc_ldms_dcgm_fp32_active":0,
    "nersc_ldms_dcgm_fp64_active":0,
    "nersc_ldms_dcgm_gr_engine_active":0.0,
    "nersc_ldms_dcgm_sm_active":0,
    "nersc_ldms_dcgm_tensor_active":0,
    "nersc_ldms_dcgm_tensor_hmma_active":0,
    "nersc_ldms_dcgm_tensor_imma_active":0
  },
  {
    "index":1,
    "timestamp":1777505995000,
    "hostname":"nid002240",
    "gpu_id":1,
    "nersc_ldms_dcgm_dram_active":0.0,
    "nersc_ldms_dcgm_fb_free":40441,
    "nersc_ldms_dcgm_fb_used":0,
    "nersc_ldms_dcgm_fp16_active":0,
    "nersc_ldms_dcgm_fp32_active":0,
    "nersc_ldms_dcgm_fp64_active":0,
    "nersc_ldms_dcgm_gr_engine_active":0.0,
    "nersc_ldms_dcgm_sm_active":0,
    "nersc_ldms_dcgm_tensor_active":0,
    "nersc_ldms_dcgm_tensor_hmma_active":0,
    "nersc_ldms_dcgm_tensor_imma_active":0
  },
  {
    "index":2,
    "timestamp":1777505995000,
    "hostname":"nid002240",
    "gpu_id":2,
    "nersc_ldms_dcgm_dram_active":0.0,
    "nersc_ldms_dcgm_fb_free":40441,
    "nersc_ldms_dcgm_fb_used":0,
    "nersc_ldms_dcgm_fp16_active":0,
    "nersc_ldms_dcgm_fp32_active":0,
    "nersc_ldms_dcgm_fp64_active":0,
    "nersc_ldms_dcgm_gr_engine_active":0.0,
    "nersc_ldms_dcgm_sm_active":0,
    "nersc_ldms_dcgm_tensor_active":0,
    "nersc_ldms_dcgm_tensor_hmma_active":0,
    "nersc_ldms_dcgm_tensor_imma_active":0
  },
  {
    "index":3,
    "timestamp":1777505995000,
    "hostname":"nid002240",
    "gpu_id":3,
    "nersc_ldms_dcgm_dram_active":0.0,
    "nersc_ldms_dcgm_fb_free":40441,
    "nersc_ldms_dcgm_fb_used":0,
    "nersc_ldms_dcgm_fp16_active":0,
    "nersc_ldms_dcgm_fp32_active":0,
    "nersc_ldms_dcgm_fp64_active":0,
    "nersc_ldms_dcgm_gr_engine_active":0.0,
    "nersc_ldms_dcgm_sm_active":0,
    "nersc_ldms_dcgm_tensor_active":0,
    "nersc_ldms_dcgm_tensor_hmma_active":0,
    "nersc_ldms_dcgm_tensor_imma_active":0
  },
  {
    "index":4,
    "timestamp":1777505995000,
    "hostname":"nid002353",
    "gpu_id":0,
    "nersc_ldms_dcgm_dram_active":0.0,
    "nersc_ldms_dcgm_fb_free":40441,
    "nersc_ldms_dcgm_fb_used":0,
    "nersc_ldms_dcgm_fp16_active":0,
    "nersc_ldms_dcgm_fp32_active":0,
    "nersc_ldms_dcgm_fp64_active":0,
    "nersc_ldms_dcgm_gr_engine_active":0.0,
    "nersc_ldms_dcgm_sm_active":0,
    "nersc_ldms_dcgm_tensor_active":0,
    "nersc_ldms_dcgm_tensor_hmma_active":0,
    "nersc_ldms_dcgm_tensor_imma_active":0
  },
  {
    "index":5,
    "timestamp":1777505995000,
    "hostname":"nid002353",
    "gpu_id":1,
    "nersc_ldms_dcgm_dram_active":0.0,
    "nersc_ldms_dcgm_fb_free":40441,
    "nersc_ldms_dcgm_fb_used":0,
    "nersc_ldms_dcgm_fp16_active":0,
    "nersc_ldms_dcgm_fp32_active":0,
    "nersc_ldms_dcgm_fp64_active":0,
    "nersc_ldms_dcgm_gr_engine_active":0.0,
    "nersc_ldms_dcgm_sm_active":0,
    "nersc_ldms_dcgm_tensor_active":0,
    "nersc_ldms_dcgm_tensor_hmma_active":0,
    "nersc_ldms_dcgm_tensor_imma_active":0
  },
  {
    "index":6,
    "timestamp":1777505995000,
    "hostname":"nid002353",
    "gpu_id":2,
    "nersc_ldms_dcgm_dram_active":0.0,
    "nersc_ldms_dcgm_fb_free":40441,
    "nersc_ldms_dcgm_fb_used":0,
    "nersc_ldms_dcgm_fp16_active":0,
    "nersc_ldms_dcgm_fp32_active":0,
    "nersc_ldms_dcgm_fp64_active":0,
    "nersc_ldms_dcgm_gr_engine_active":0.0,
    "nersc_ldms_dcgm_sm_active":0,
    "nersc_ldms_dcgm_tensor_active":0,
    "nersc_ldms_dcgm_tensor_hmma_active":0,
    "nersc_ldms_dcgm_tensor_imma_active":0
  },
  {
    "index":7,
    "timestamp":1777505995000,
    "hostname":"nid002353",
    "gpu_id":3,
    "nersc_ldms_dcgm_dram_active":7.358e-16,
    "nersc_ldms_dcgm_fb_free":40441,
    "nersc_ldms_dcgm_fb_used":0,
    "nersc_ldms_dcgm_fp16_active":0,
    "nersc_ldms_dcgm_fp32_active":0,
    "nersc_ldms_dcgm_fp64_active":0,
    "nersc_ldms_dcgm_gr_engine_active":0.0,
    "nersc_ldms_dcgm_sm_active":0,
    "nersc_ldms_dcgm_tensor_active":0,
    "nersc_ldms_dcgm_tensor_hmma_active":0,
    "nersc_ldms_dcgm_tensor_imma_active":0
  },
  {
    "index":8,
    "timestamp":1777506005000,
    "hostname":"nid002240",
    "gpu_id":0,
    "nersc_ldms_dcgm_dram_active":0.0000000124,
    "nersc_ldms_dcgm_fb_free":40441,
    "nersc_ldms_dcgm_fb_used":1694,
    "nersc_ldms_dcgm_fp16_active":0,
    "nersc_ldms_dcgm_fp32_active":0,
    "nersc_ldms_dcgm_fp64_active":0,
    "nersc_ldms_dcgm_gr_engine_active":0.0,
    "nersc_ldms_dcgm_sm_active":0,
    "nersc_ldms_dcgm_tensor_active":0,
    "nersc_ldms_dcgm_tensor_hmma_active":0,
    "nersc_ldms_dcgm_tensor_imma_active":0
  },
  {
    "index":9,
    "timestamp":1777506005000,
    "hostname":"nid002240",
    "gpu_id":1,
    "nersc_ldms_dcgm_dram_active":0.0000000115,
    "nersc_ldms_dcgm_fb_free":40437,
    "nersc_ldms_dcgm_fb_used":1694,
    "nersc_ldms_dcgm_fp16_active":0,
    "nersc_ldms_dcgm_fp32_active":0,
    "nersc_ldms_dcgm_fp64_active":0,
    "nersc_ldms_dcgm_gr_engine_active":0.0,
    "nersc_ldms_dcgm_sm_active":0,
    "nersc_ldms_dcgm_tensor_active":0,
    "nersc_ldms_dcgm_tensor_hmma_active":0,
    "nersc_ldms_dcgm_tensor_imma_active":0
  },
  {
    "index":10,
    "timestamp":1777506005000,
    "hostname":"nid002240",
    "gpu_id":2,
    "nersc_ldms_dcgm_dram_active":0.0000000026,
    "nersc_ldms_dcgm_fb_free":40441,
    "nersc_ldms_dcgm_fb_used":1694,
    "nersc_ldms_dcgm_fp16_active":0,
    "nersc_ldms_dcgm_fp32_active":0,
    "nersc_ldms_dcgm_fp64_active":0,
    "nersc_ldms_dcgm_gr_engine_active":0.0,
    "nersc_ldms_dcgm_sm_active":0,
    "nersc_ldms_dcgm_tensor_active":0,
    "nersc_ldms_dcgm_tensor_hmma_active":0,
    "nersc_ldms_dcgm_tensor_imma_active":0
  },
  {
    "index":11,
    "timestamp":1777506005000,
    "hostname":"nid002240",
    "gpu_id":3,
    "nersc_ldms_dcgm_dram_active":0.0000000015,
    "nersc_ldms_dcgm_fb_free":40370,
    "nersc_ldms_dcgm_fb_used":0,
    "nersc_ldms_dcgm_fp16_active":0,
    "nersc_ldms_dcgm_fp32_active":0,
    "nersc_ldms_dcgm_fp64_active":0,
    "nersc_ldms_dcgm_gr_engine_active":0.0,
    "nersc_ldms_dcgm_sm_active":0,
    "nersc_ldms_dcgm_tensor_active":0,
    "nersc_ldms_dcgm_tensor_hmma_active":0,
    "nersc_ldms_dcgm_tensor_imma_active":0
  },
  {
    "index":12,
    "timestamp":1777506005000,
    "hostname":"nid002353",
    "gpu_id":0,
    "nersc_ldms_dcgm_dram_active":0.0000001264,
    "nersc_ldms_dcgm_fb_free":38747,
    "nersc_ldms_dcgm_fb_used":4,
    "nersc_ldms_dcgm_fp16_active":0,
    "nersc_ldms_dcgm_fp32_active":0,
    "nersc_ldms_dcgm_fp64_active":0,
    "nersc_ldms_dcgm_gr_engine_active":0.0000002921,
    "nersc_ldms_dcgm_sm_active":0,
    "nersc_ldms_dcgm_tensor_active":0,
    "nersc_ldms_dcgm_tensor_hmma_active":0,
    "nersc_ldms_dcgm_tensor_imma_active":0
  },
  {
    "index":13,
    "timestamp":1777506005000,
    "hostname":"nid002353",
    "gpu_id":1,
    "nersc_ldms_dcgm_dram_active":0.0000098535,
    "nersc_ldms_dcgm_fb_free":40441,
    "nersc_ldms_dcgm_fb_used":4,
    "nersc_ldms_dcgm_fp16_active":0,
    "nersc_ldms_dcgm_fp32_active":0,
    "nersc_ldms_dcgm_fp64_active":0,
    "nersc_ldms_dcgm_gr_engine_active":0.0,
    "nersc_ldms_dcgm_sm_active":0,
    "nersc_ldms_dcgm_tensor_active":0,
    "nersc_ldms_dcgm_tensor_hmma_active":0,
    "nersc_ldms_dcgm_tensor_imma_active":0
  },
  {
    "index":14,
    "timestamp":1777506005000,
    "hostname":"nid002353",
    "gpu_id":2,
    "nersc_ldms_dcgm_dram_active":0.0000000065,
    "nersc_ldms_dcgm_fb_free":38747,
    "nersc_ldms_dcgm_fb_used":0,
    "nersc_ldms_dcgm_fp16_active":0,
    "nersc_ldms_dcgm_fp32_active":0,
    "nersc_ldms_dcgm_fp64_active":0,
    "nersc_ldms_dcgm_gr_engine_active":0.0,
    "nersc_ldms_dcgm_sm_active":0,
    "nersc_ldms_dcgm_tensor_active":0,
    "nersc_ldms_dcgm_tensor_hmma_active":0,
    "nersc_ldms_dcgm_tensor_imma_active":0
  },
  {
    "index":15,
    "timestamp":1777506005000,
    "hostname":"nid002353",
    "gpu_id":3,
    "nersc_ldms_dcgm_dram_active":0.0000018875,
    "nersc_ldms_dcgm_fb_free":38747,
    "nersc_ldms_dcgm_fb_used":0,
    "nersc_ldms_dcgm_fp16_active":0,
    "nersc_ldms_dcgm_fp32_active":0,
    "nersc_ldms_dcgm_fp64_active":0,
    "nersc_ldms_dcgm_gr_engine_active":0.0002419182,
    "nersc_ldms_dcgm_sm_active":0,
    "nersc_ldms_dcgm_tensor_active":0,
    "nersc_ldms_dcgm_tensor_hmma_active":0,
    "nersc_ldms_dcgm_tensor_imma_active":0
  },
  {
    "index":16,
    "timestamp":1777506015000,
    "hostname":"nid002240",
    "gpu_id":0,
    "nersc_ldms_dcgm_dram_active":0.0000000076,
    "nersc_ldms_dcgm_fb_free":38747,
    "nersc_ldms_dcgm_fb_used":1694,
    "nersc_ldms_dcgm_fp16_active":0,
    "nersc_ldms_dcgm_fp32_active":0,
    "nersc_ldms_dcgm_fp64_active":0,
    "nersc_ldms_dcgm_gr_engine_active":0.0000000099,
    "nersc_ldms_dcgm_sm_active":0,
    "nersc_ldms_dcgm_tensor_active":0,
    "nersc_ldms_dcgm_tensor_hmma_active":0,
    "nersc_ldms_dcgm_tensor_imma_active":0
  },
  {
    "index":17,
    "timestamp":1777506015000,
    "hostname":"nid002240",
    "gpu_id":1,
    "nersc_ldms_dcgm_dram_active":0.0000001353,
    "nersc_ldms_dcgm_fb_free":38747,
    "nersc_ldms_dcgm_fb_used":1694,
    "nersc_ldms_dcgm_fp16_active":0,
    "nersc_ldms_dcgm_fp32_active":0,
    "nersc_ldms_dcgm_fp64_active":0,
    "nersc_ldms_dcgm_gr_engine_active":0.0000000222,
    "nersc_ldms_dcgm_sm_active":0,
    "nersc_ldms_dcgm_tensor_active":0,
    "nersc_ldms_dcgm_tensor_hmma_active":0,
    "nersc_ldms_dcgm_tensor_imma_active":0
  },
  {
    "index":18,
    "timestamp":1777506015000,
    "hostname":"nid002240",
    "gpu_id":2,
    "nersc_ldms_dcgm_dram_active":0.0000000676,
    "nersc_ldms_dcgm_fb_free":38747,
    "nersc_ldms_dcgm_fb_used":1694,
    "nersc_ldms_dcgm_fp16_active":0,
    "nersc_ldms_dcgm_fp32_active":0,
    "nersc_ldms_dcgm_fp64_active":0,
    "nersc_ldms_dcgm_gr_engine_active":0.0000000495,
    "nersc_ldms_dcgm_sm_active":0,
    "nersc_ldms_dcgm_tensor_active":0,
    "nersc_ldms_dcgm_tensor_hmma_active":0,
    "nersc_ldms_dcgm_tensor_imma_active":0
  },
  {
    "index":19,
    "timestamp":1777506015000,
    "hostname":"nid002240",
    "gpu_id":3,
    "nersc_ldms_dcgm_dram_active":0.0000000145,
    "nersc_ldms_dcgm_fb_free":38747,
    "nersc_ldms_dcgm_fb_used":1694,
    "nersc_ldms_dcgm_fp16_active":0,
    "nersc_ldms_dcgm_fp32_active":0,
    "nersc_ldms_dcgm_fp64_active":0,
    "nersc_ldms_dcgm_gr_engine_active":0.0000001086,
    "nersc_ldms_dcgm_sm_active":0,
    "nersc_ldms_dcgm_tensor_active":0,
    "nersc_ldms_dcgm_tensor_hmma_active":0,
    "nersc_ldms_dcgm_tensor_imma_active":0
  },
  {
    "index":20,
    "timestamp":1777506015000,
    "hostname":"nid002353",
    "gpu_id":0,
    "nersc_ldms_dcgm_dram_active":0.000000129,
    "nersc_ldms_dcgm_fb_free":38747,
    "nersc_ldms_dcgm_fb_used":1694,
    "nersc_ldms_dcgm_fp16_active":0,
    "nersc_ldms_dcgm_fp32_active":0,
    "nersc_ldms_dcgm_fp64_active":0,
    "nersc_ldms_dcgm_gr_engine_active":0.0,
    "nersc_ldms_dcgm_sm_active":0,
    "nersc_ldms_dcgm_tensor_active":0,
    "nersc_ldms_dcgm_tensor_hmma_active":0,
    "nersc_ldms_dcgm_tensor_imma_active":0
  },
  {
    "index":21,
    "timestamp":1777506015000,
    "hostname":"nid002353",
    "gpu_id":1,
    "nersc_ldms_dcgm_dram_active":0.0000000434,
    "nersc_ldms_dcgm_fb_free":38747,
    "nersc_ldms_dcgm_fb_used":1694,
    "nersc_ldms_dcgm_fp16_active":0,
    "nersc_ldms_dcgm_fp32_active":0,
    "nersc_ldms_dcgm_fp64_active":0,
    "nersc_ldms_dcgm_gr_engine_active":0.0000000019,
    "nersc_ldms_dcgm_sm_active":0,
    "nersc_ldms_dcgm_tensor_active":0,
    "nersc_ldms_dcgm_tensor_hmma_active":0,
    "nersc_ldms_dcgm_tensor_imma_active":0
  },
  {
    "index":22,
    "timestamp":1777506015000,
    "hostname":"nid002353",
    "gpu_id":2,
    "nersc_ldms_dcgm_dram_active":0.000000127,
    "nersc_ldms_dcgm_fb_free":38747,
    "nersc_ldms_dcgm_fb_used":1694,
    "nersc_ldms_dcgm_fp16_active":0,
    "nersc_ldms_dcgm_fp32_active":0,
    "nersc_ldms_dcgm_fp64_active":0,
    "nersc_ldms_dcgm_gr_engine_active":0.0000000023,
    "nersc_ldms_dcgm_sm_active":0,
    "nersc_ldms_dcgm_tensor_active":0,
    "nersc_ldms_dcgm_tensor_hmma_active":0,
    "nersc_ldms_dcgm_tensor_imma_active":0
  },
  {
    "index":23,
    "timestamp":1777506015000,
    "hostname":"nid002353",
    "gpu_id":3,
    "nersc_ldms_dcgm_dram_active":0.0000000884,
    "nersc_ldms_dcgm_fb_free":38747,
    "nersc_ldms_dcgm_fb_used":1694,
    "nersc_ldms_dcgm_fp16_active":0,
    "nersc_ldms_dcgm_fp32_active":0,
    "nersc_ldms_dcgm_fp64_active":0,
    "nersc_ldms_dcgm_gr_engine_active":0.0,
    "nersc_ldms_dcgm_sm_active":0,
    "nersc_ldms_dcgm_tensor_active":0,
    "nersc_ldms_dcgm_tensor_hmma_active":0,
    "nersc_ldms_dcgm_tensor_imma_active":0
  },
  {
    "index":24,
    "timestamp":1777506025000,
    "hostname":"nid002240",
    "gpu_id":0,
    "nersc_ldms_dcgm_dram_active":0.0000000059,
    "nersc_ldms_dcgm_fb_free":38747,
    "nersc_ldms_dcgm_fb_used":1694,
    "nersc_ldms_dcgm_fp16_active":0,
    "nersc_ldms_dcgm_fp32_active":0,
    "nersc_ldms_dcgm_fp64_active":0,
    "nersc_ldms_dcgm_gr_engine_active":0.0,
    "nersc_ldms_dcgm_sm_active":0,
    "nersc_ldms_dcgm_tensor_active":0,
    "nersc_ldms_dcgm_tensor_hmma_active":0,
    "nersc_ldms_dcgm_tensor_imma_active":0
  },
  {
    "index":25,
    "timestamp":1777506025000,
    "hostname":"nid002240",
    "gpu_id":1,
    "nersc_ldms_dcgm_dram_active":0.0000001201,
    "nersc_ldms_dcgm_fb_free":38747,
    "nersc_ldms_dcgm_fb_used":1694,
    "nersc_ldms_dcgm_fp16_active":0,
    "nersc_ldms_dcgm_fp32_active":0,
    "nersc_ldms_dcgm_fp64_active":0,
    "nersc_ldms_dcgm_gr_engine_active":0.0,
    "nersc_ldms_dcgm_sm_active":0,
    "nersc_ldms_dcgm_tensor_active":0,
    "nersc_ldms_dcgm_tensor_hmma_active":0,
    "nersc_ldms_dcgm_tensor_imma_active":0
  },
  {
    "index":26,
    "timestamp":1777506025000,
    "hostname":"nid002240",
    "gpu_id":2,
    "nersc_ldms_dcgm_dram_active":0.000000065,
    "nersc_ldms_dcgm_fb_free":38747,
    "nersc_ldms_dcgm_fb_used":1694,
    "nersc_ldms_dcgm_fp16_active":0,
    "nersc_ldms_dcgm_fp32_active":0,
    "nersc_ldms_dcgm_fp64_active":0,
    "nersc_ldms_dcgm_gr_engine_active":0.0,
    "nersc_ldms_dcgm_sm_active":0,
    "nersc_ldms_dcgm_tensor_active":0,
    "nersc_ldms_dcgm_tensor_hmma_active":0,
    "nersc_ldms_dcgm_tensor_imma_active":0
  },
  {
    "index":27,
    "timestamp":1777506025000,
    "hostname":"nid002240",
    "gpu_id":3,
    "nersc_ldms_dcgm_dram_active":0.0000000108,
    "nersc_ldms_dcgm_fb_free":38747,
    "nersc_ldms_dcgm_fb_used":1694,
    "nersc_ldms_dcgm_fp16_active":0,
    "nersc_ldms_dcgm_fp32_active":0,
    "nersc_ldms_dcgm_fp64_active":0,
    "nersc_ldms_dcgm_gr_engine_active":0.0,
    "nersc_ldms_dcgm_sm_active":0,
    "nersc_ldms_dcgm_tensor_active":0,
    "nersc_ldms_dcgm_tensor_hmma_active":0,
    "nersc_ldms_dcgm_tensor_imma_active":0
  },
  {
    "index":28,
    "timestamp":1777506025000,
    "hostname":"nid002353",
    "gpu_id":0,
    "nersc_ldms_dcgm_dram_active":0.000000187,
    "nersc_ldms_dcgm_fb_free":38747,
    "nersc_ldms_dcgm_fb_used":1694,
    "nersc_ldms_dcgm_fp16_active":0,
    "nersc_ldms_dcgm_fp32_active":0,
    "nersc_ldms_dcgm_fp64_active":0,
    "nersc_ldms_dcgm_gr_engine_active":0.0,
    "nersc_ldms_dcgm_sm_active":0,
    "nersc_ldms_dcgm_tensor_active":0,
    "nersc_ldms_dcgm_tensor_hmma_active":0,
    "nersc_ldms_dcgm_tensor_imma_active":0
  },
  {
    "index":29,
    "timestamp":1777506025000,
    "hostname":"nid002353",
    "gpu_id":1,
    "nersc_ldms_dcgm_dram_active":0.0000000457,
    "nersc_ldms_dcgm_fb_free":38747,
    "nersc_ldms_dcgm_fb_used":1694,
    "nersc_ldms_dcgm_fp16_active":0,
    "nersc_ldms_dcgm_fp32_active":0,
    "nersc_ldms_dcgm_fp64_active":0,
    "nersc_ldms_dcgm_gr_engine_active":0.0,
    "nersc_ldms_dcgm_sm_active":0,
    "nersc_ldms_dcgm_tensor_active":0,
    "nersc_ldms_dcgm_tensor_hmma_active":0,
    "nersc_ldms_dcgm_tensor_imma_active":0
  },
  {
    "index":30,
    "timestamp":1777506025000,
    "hostname":"nid002353",
    "gpu_id":2,
    "nersc_ldms_dcgm_dram_active":0.0000001469,
    "nersc_ldms_dcgm_fb_free":38747,
    "nersc_ldms_dcgm_fb_used":1694,
    "nersc_ldms_dcgm_fp16_active":0,
    "nersc_ldms_dcgm_fp32_active":0,
    "nersc_ldms_dcgm_fp64_active":0,
    "nersc_ldms_dcgm_gr_engine_active":0.0,
    "nersc_ldms_dcgm_sm_active":0,
    "nersc_ldms_dcgm_tensor_active":0,
    "nersc_ldms_dcgm_tensor_hmma_active":0,
    "nersc_ldms_dcgm_tensor_imma_active":0
  },
  {
    "index":31,
    "timestamp":1777506025000,
    "hostname":"nid002353",
    "gpu_id":3,
    "nersc_ldms_dcgm_dram_active":0.0000000881,
    "nersc_ldms_dcgm_fb_free":38747,
    "nersc_ldms_dcgm_fb_used":1694,
    "nersc_ldms_dcgm_fp16_active":0,
    "nersc_ldms_dcgm_fp32_active":0,
    "nersc_ldms_dcgm_fp64_active":0,
    "nersc_ldms_dcgm_gr_engine_active":0.0,
    "nersc_ldms_dcgm_sm_active":0,
    "nersc_ldms_dcgm_tensor_active":0,
    "nersc_ldms_dcgm_tensor_hmma_active":0,
    "nersc_ldms_dcgm_tensor_imma_active":0
  },
  {
    "index":32,
    "timestamp":1777506035000,
    "hostname":"nid002240",
    "gpu_id":0,
    "nersc_ldms_dcgm_dram_active":0.0000000081,
    "nersc_ldms_dcgm_fb_free":38747,
    "nersc_ldms_dcgm_fb_used":1694,
    "nersc_ldms_dcgm_fp16_active":0,
    "nersc_ldms_dcgm_fp32_active":0,
    "nersc_ldms_dcgm_fp64_active":0,
    "nersc_ldms_dcgm_gr_engine_active":0.0,
    "nersc_ldms_dcgm_sm_active":0,
    "nersc_ldms_dcgm_tensor_active":0,
    "nersc_ldms_dcgm_tensor_hmma_active":0,
    "nersc_ldms_dcgm_tensor_imma_active":0
  },
  {
    "index":33,
    "timestamp":1777506035000,
    "hostname":"nid002240",
    "gpu_id":1,
    "nersc_ldms_dcgm_dram_active":0.0000001224,
    "nersc_ldms_dcgm_fb_free":38747,
    "nersc_ldms_dcgm_fb_used":1694,
    "nersc_ldms_dcgm_fp16_active":0,
    "nersc_ldms_dcgm_fp32_active":0,
    "nersc_ldms_dcgm_fp64_active":0,
    "nersc_ldms_dcgm_gr_engine_active":0.0,
    "nersc_ldms_dcgm_sm_active":0,
    "nersc_ldms_dcgm_tensor_active":0,
    "nersc_ldms_dcgm_tensor_hmma_active":0,
    "nersc_ldms_dcgm_tensor_imma_active":0
  },
  {
    "index":34,
    "timestamp":1777506035000,
    "hostname":"nid002240",
    "gpu_id":2,
    "nersc_ldms_dcgm_dram_active":0.0000000549,
    "nersc_ldms_dcgm_fb_free":38747,
    "nersc_ldms_dcgm_fb_used":1694,
    "nersc_ldms_dcgm_fp16_active":0,
    "nersc_ldms_dcgm_fp32_active":0,
    "nersc_ldms_dcgm_fp64_active":0,
    "nersc_ldms_dcgm_gr_engine_active":0.0,
    "nersc_ldms_dcgm_sm_active":0,
    "nersc_ldms_dcgm_tensor_active":0,
    "nersc_ldms_dcgm_tensor_hmma_active":0,
    "nersc_ldms_dcgm_tensor_imma_active":0
  },
  {
    "index":35,
    "timestamp":1777506035000,
    "hostname":"nid002240",
    "gpu_id":3,
    "nersc_ldms_dcgm_dram_active":0.0000000113,
    "nersc_ldms_dcgm_fb_free":38747,
    "nersc_ldms_dcgm_fb_used":1694,
    "nersc_ldms_dcgm_fp16_active":0,
    "nersc_ldms_dcgm_fp32_active":0,
    "nersc_ldms_dcgm_fp64_active":0,
    "nersc_ldms_dcgm_gr_engine_active":0.0,
    "nersc_ldms_dcgm_sm_active":0,
    "nersc_ldms_dcgm_tensor_active":0,
    "nersc_ldms_dcgm_tensor_hmma_active":0,
    "nersc_ldms_dcgm_tensor_imma_active":0
  },
  {
    "index":36,
    "timestamp":1777506035000,
    "hostname":"nid002353",
    "gpu_id":0,
    "nersc_ldms_dcgm_dram_active":0.0000001113,
    "nersc_ldms_dcgm_fb_free":38747,
    "nersc_ldms_dcgm_fb_used":1694,
    "nersc_ldms_dcgm_fp16_active":0,
    "nersc_ldms_dcgm_fp32_active":0,
    "nersc_ldms_dcgm_fp64_active":0,
    "nersc_ldms_dcgm_gr_engine_active":0.0,
    "nersc_ldms_dcgm_sm_active":0,
    "nersc_ldms_dcgm_tensor_active":0,
    "nersc_ldms_dcgm_tensor_hmma_active":0,
    "nersc_ldms_dcgm_tensor_imma_active":0
  },
  {
    "index":37,
    "timestamp":1777506035000,
    "hostname":"nid002353",
    "gpu_id":1,
    "nersc_ldms_dcgm_dram_active":0.0000000433,
    "nersc_ldms_dcgm_fb_free":38747,
    "nersc_ldms_dcgm_fb_used":1694,
    "nersc_ldms_dcgm_fp16_active":0,
    "nersc_ldms_dcgm_fp32_active":0,
    "nersc_ldms_dcgm_fp64_active":0,
    "nersc_ldms_dcgm_gr_engine_active":0.0,
    "nersc_ldms_dcgm_sm_active":0,
    "nersc_ldms_dcgm_tensor_active":0,
    "nersc_ldms_dcgm_tensor_hmma_active":0,
    "nersc_ldms_dcgm_tensor_imma_active":0
  },
  {
    "index":38,
    "timestamp":1777506035000,
    "hostname":"nid002353",
    "gpu_id":2,
    "nersc_ldms_dcgm_dram_active":0.0000001393,
    "nersc_ldms_dcgm_fb_free":38747,
    "nersc_ldms_dcgm_fb_used":1694,
    "nersc_ldms_dcgm_fp16_active":0,
    "nersc_ldms_dcgm_fp32_active":0,
    "nersc_ldms_dcgm_fp64_active":0,
    "nersc_ldms_dcgm_gr_engine_active":0.0,
    "nersc_ldms_dcgm_sm_active":0,
    "nersc_ldms_dcgm_tensor_active":0,
    "nersc_ldms_dcgm_tensor_hmma_active":0,
    "nersc_ldms_dcgm_tensor_imma_active":0
  },
  {
    "index":39,
    "timestamp":1777506035000,
    "hostname":"nid002353",
    "gpu_id":3,
    "nersc_ldms_dcgm_dram_active":0.0000000889,
    "nersc_ldms_dcgm_fb_free":38747,
    "nersc_ldms_dcgm_fb_used":1694,
    "nersc_ldms_dcgm_fp16_active":0,
    "nersc_ldms_dcgm_fp32_active":0,
    "nersc_ldms_dcgm_fp64_active":0,
    "nersc_ldms_dcgm_gr_engine_active":0.0,
    "nersc_ldms_dcgm_sm_active":0,
    "nersc_ldms_dcgm_tensor_active":0,
    "nersc_ldms_dcgm_tensor_hmma_active":0,
    "nersc_ldms_dcgm_tensor_imma_active":0
  },
  {
    "index":40,
    "timestamp":1777506045000,
    "hostname":"nid002240",
    "gpu_id":0,
    "nersc_ldms_dcgm_dram_active":0.000000008,
    "nersc_ldms_dcgm_fb_free":38747,
    "nersc_ldms_dcgm_fb_used":1694,
    "nersc_ldms_dcgm_fp16_active":0,
    "nersc_ldms_dcgm_fp32_active":0,
    "nersc_ldms_dcgm_fp64_active":0,
    "nersc_ldms_dcgm_gr_engine_active":0.0,
    "nersc_ldms_dcgm_sm_active":0,
    "nersc_ldms_dcgm_tensor_active":0,
    "nersc_ldms_dcgm_tensor_hmma_active":0,
    "nersc_ldms_dcgm_tensor_imma_active":0
  },
  {
    "index":41,
    "timestamp":1777506045000,
    "hostname":"nid002240",
    "gpu_id":1,
    "nersc_ldms_dcgm_dram_active":0.0000001224,
    "nersc_ldms_dcgm_fb_free":38747,
    "nersc_ldms_dcgm_fb_used":1694,
    "nersc_ldms_dcgm_fp16_active":0,
    "nersc_ldms_dcgm_fp32_active":0,
    "nersc_ldms_dcgm_fp64_active":0,
    "nersc_ldms_dcgm_gr_engine_active":0.0,
    "nersc_ldms_dcgm_sm_active":0,
    "nersc_ldms_dcgm_tensor_active":0,
    "nersc_ldms_dcgm_tensor_hmma_active":0,
    "nersc_ldms_dcgm_tensor_imma_active":0
  },
  {
    "index":42,
    "timestamp":1777506045000,
    "hostname":"nid002240",
    "gpu_id":2,
    "nersc_ldms_dcgm_dram_active":0.0000000618,
    "nersc_ldms_dcgm_fb_free":38747,
    "nersc_ldms_dcgm_fb_used":1694,
    "nersc_ldms_dcgm_fp16_active":0,
    "nersc_ldms_dcgm_fp32_active":0,
    "nersc_ldms_dcgm_fp64_active":0,
    "nersc_ldms_dcgm_gr_engine_active":0.0,
    "nersc_ldms_dcgm_sm_active":0,
    "nersc_ldms_dcgm_tensor_active":0,
    "nersc_ldms_dcgm_tensor_hmma_active":0,
    "nersc_ldms_dcgm_tensor_imma_active":0
  },
  {
    "index":43,
    "timestamp":1777506045000,
    "hostname":"nid002240",
    "gpu_id":3,
    "nersc_ldms_dcgm_dram_active":0.0000000106,
    "nersc_ldms_dcgm_fb_free":38747,
    "nersc_ldms_dcgm_fb_used":1694,
    "nersc_ldms_dcgm_fp16_active":0,
    "nersc_ldms_dcgm_fp32_active":0,
    "nersc_ldms_dcgm_fp64_active":0,
    "nersc_ldms_dcgm_gr_engine_active":0.0,
    "nersc_ldms_dcgm_sm_active":0,
    "nersc_ldms_dcgm_tensor_active":0,
    "nersc_ldms_dcgm_tensor_hmma_active":0,
    "nersc_ldms_dcgm_tensor_imma_active":0
  },
  {
    "index":44,
    "timestamp":1777506045000,
    "hostname":"nid002353",
    "gpu_id":0,
    "nersc_ldms_dcgm_dram_active":0.0000001207,
    "nersc_ldms_dcgm_fb_free":38747,
    "nersc_ldms_dcgm_fb_used":1694,
    "nersc_ldms_dcgm_fp16_active":0,
    "nersc_ldms_dcgm_fp32_active":0,
    "nersc_ldms_dcgm_fp64_active":0,
    "nersc_ldms_dcgm_gr_engine_active":0.0,
    "nersc_ldms_dcgm_sm_active":0,
    "nersc_ldms_dcgm_tensor_active":0,
    "nersc_ldms_dcgm_tensor_hmma_active":0,
    "nersc_ldms_dcgm_tensor_imma_active":0
  },
  {
    "index":45,
    "timestamp":1777506045000,
    "hostname":"nid002353",
    "gpu_id":1,
    "nersc_ldms_dcgm_dram_active":0.0000000437,
    "nersc_ldms_dcgm_fb_free":38747,
    "nersc_ldms_dcgm_fb_used":1694,
    "nersc_ldms_dcgm_fp16_active":0,
    "nersc_ldms_dcgm_fp32_active":0,
    "nersc_ldms_dcgm_fp64_active":0,
    "nersc_ldms_dcgm_gr_engine_active":0.0,
    "nersc_ldms_dcgm_sm_active":0,
    "nersc_ldms_dcgm_tensor_active":0,
    "nersc_ldms_dcgm_tensor_hmma_active":0,
    "nersc_ldms_dcgm_tensor_imma_active":0
  },
  {
    "index":46,
    "timestamp":1777506045000,
    "hostname":"nid002353",
    "gpu_id":2,
    "nersc_ldms_dcgm_dram_active":0.0000001304,
    "nersc_ldms_dcgm_fb_free":38747,
    "nersc_ldms_dcgm_fb_used":1694,
    "nersc_ldms_dcgm_fp16_active":0,
    "nersc_ldms_dcgm_fp32_active":0,
    "nersc_ldms_dcgm_fp64_active":0,
    "nersc_ldms_dcgm_gr_engine_active":0.0,
    "nersc_ldms_dcgm_sm_active":0,
    "nersc_ldms_dcgm_tensor_active":0,
    "nersc_ldms_dcgm_tensor_hmma_active":0,
    "nersc_ldms_dcgm_tensor_imma_active":0
  },
  {
    "index":47,
    "timestamp":1777506045000,
    "hostname":"nid002353",
    "gpu_id":3,
    "nersc_ldms_dcgm_dram_active":0.0000000799,
    "nersc_ldms_dcgm_fb_free":38747,
    "nersc_ldms_dcgm_fb_used":1694,
    "nersc_ldms_dcgm_fp16_active":0,
    "nersc_ldms_dcgm_fp32_active":0,
    "nersc_ldms_dcgm_fp64_active":0,
    "nersc_ldms_dcgm_gr_engine_active":0.0,
    "nersc_ldms_dcgm_sm_active":0,
    "nersc_ldms_dcgm_tensor_active":0,
    "nersc_ldms_dcgm_tensor_hmma_active":0,
    "nersc_ldms_dcgm_tensor_imma_active":0
  },
  {
    "index":48,
    "timestamp":1777506055000,
    "hostname":"nid002240",
    "gpu_id":0,
    "nersc_ldms_dcgm_dram_active":0.0000000067,
    "nersc_ldms_dcgm_fb_free":38747,
    "nersc_ldms_dcgm_fb_used":1694,
    "nersc_ldms_dcgm_fp16_active":0,
    "nersc_ldms_dcgm_fp32_active":0,
    "nersc_ldms_dcgm_fp64_active":0,
    "nersc_ldms_dcgm_gr_engine_active":0.0,
    "nersc_ldms_dcgm_sm_active":0,
    "nersc_ldms_dcgm_tensor_active":0,
    "nersc_ldms_dcgm_tensor_hmma_active":0,
    "nersc_ldms_dcgm_tensor_imma_active":0
  },
  {
    "index":49,
    "timestamp":1777506055000,
    "hostname":"nid002353",
    "gpu_id":0,
    "nersc_ldms_dcgm_dram_active":0.0000001242,
    "nersc_ldms_dcgm_fb_free":38747,
    "nersc_ldms_dcgm_fb_used":1694,
    "nersc_ldms_dcgm_fp16_active":0,
    "nersc_ldms_dcgm_fp32_active":0,
    "nersc_ldms_dcgm_fp64_active":0,
    "nersc_ldms_dcgm_gr_engine_active":0.0,
    "nersc_ldms_dcgm_sm_active":0,
    "nersc_ldms_dcgm_tensor_active":0,
    "nersc_ldms_dcgm_tensor_hmma_active":0,
    "nersc_ldms_dcgm_tensor_imma_active":0
  },
  {
    "index":50,
    "timestamp":1777506065000,
    "hostname":"nid002240",
    "gpu_id":0,
    "nersc_ldms_dcgm_dram_active":0.0000000065,
    "nersc_ldms_dcgm_fb_free":38747,
    "nersc_ldms_dcgm_fb_used":1694,
    "nersc_ldms_dcgm_fp16_active":0,
    "nersc_ldms_dcgm_fp32_active":0,
    "nersc_ldms_dcgm_fp64_active":0,
    "nersc_ldms_dcgm_gr_engine_active":0.0,
    "nersc_ldms_dcgm_sm_active":0,
    "nersc_ldms_dcgm_tensor_active":0,
    "nersc_ldms_dcgm_tensor_hmma_active":0,
    "nersc_ldms_dcgm_tensor_imma_active":0
  },
  {
    "index":51,
    "timestamp":1777506065000,
    "hostname":"nid002240",
    "gpu_id":1,
    "nersc_ldms_dcgm_dram_active":0.0000001249,
    "nersc_ldms_dcgm_fb_free":38747,
    "nersc_ldms_dcgm_fb_used":1694,
    "nersc_ldms_dcgm_fp16_active":0,
    "nersc_ldms_dcgm_fp32_active":0,
    "nersc_ldms_dcgm_fp64_active":0,
    "nersc_ldms_dcgm_gr_engine_active":0.0,
    "nersc_ldms_dcgm_sm_active":0,
    "nersc_ldms_dcgm_tensor_active":0,
    "nersc_ldms_dcgm_tensor_hmma_active":0,
    "nersc_ldms_dcgm_tensor_imma_active":0
  },
  {
    "index":52,
    "timestamp":1777506065000,
    "hostname":"nid002240",
    "gpu_id":2,
    "nersc_ldms_dcgm_dram_active":0.0000000601,
    "nersc_ldms_dcgm_fb_free":38747,
    "nersc_ldms_dcgm_fb_used":1694,
    "nersc_ldms_dcgm_fp16_active":0,
    "nersc_ldms_dcgm_fp32_active":0,
    "nersc_ldms_dcgm_fp64_active":0,
    "nersc_ldms_dcgm_gr_engine_active":0.0,
    "nersc_ldms_dcgm_sm_active":0,
    "nersc_ldms_dcgm_tensor_active":0,
    "nersc_ldms_dcgm_tensor_hmma_active":0,
    "nersc_ldms_dcgm_tensor_imma_active":0
  },
  {
    "index":53,
    "timestamp":1777506065000,
    "hostname":"nid002240",
    "gpu_id":3,
    "nersc_ldms_dcgm_dram_active":0.0000000116,
    "nersc_ldms_dcgm_fb_free":38747,
    "nersc_ldms_dcgm_fb_used":1694,
    "nersc_ldms_dcgm_fp16_active":0,
    "nersc_ldms_dcgm_fp32_active":0,
    "nersc_ldms_dcgm_fp64_active":0,
    "nersc_ldms_dcgm_gr_engine_active":0.0,
    "nersc_ldms_dcgm_sm_active":0,
    "nersc_ldms_dcgm_tensor_active":0,
    "nersc_ldms_dcgm_tensor_hmma_active":0,
    "nersc_ldms_dcgm_tensor_imma_active":0
  },
  {
    "index":54,
    "timestamp":1777506065000,
    "hostname":"nid002353",
    "gpu_id":0,
    "nersc_ldms_dcgm_dram_active":0.000000121,
    "nersc_ldms_dcgm_fb_free":38747,
    "nersc_ldms_dcgm_fb_used":1694,
    "nersc_ldms_dcgm_fp16_active":0,
    "nersc_ldms_dcgm_fp32_active":0,
    "nersc_ldms_dcgm_fp64_active":0,
    "nersc_ldms_dcgm_gr_engine_active":0.0,
    "nersc_ldms_dcgm_sm_active":0,
    "nersc_ldms_dcgm_tensor_active":0,
    "nersc_ldms_dcgm_tensor_hmma_active":0,
    "nersc_ldms_dcgm_tensor_imma_active":0
  },
  {
    "index":55,
    "timestamp":1777506065000,
    "hostname":"nid002353",
    "gpu_id":1,
    "nersc_ldms_dcgm_dram_active":0.0000000463,
    "nersc_ldms_dcgm_fb_free":38747,
    "nersc_ldms_dcgm_fb_used":1694,
    "nersc_ldms_dcgm_fp16_active":0,
    "nersc_ldms_dcgm_fp32_active":0,
    "nersc_ldms_dcgm_fp64_active":0,
    "nersc_ldms_dcgm_gr_engine_active":0.0,
    "nersc_ldms_dcgm_sm_active":0,
    "nersc_ldms_dcgm_tensor_active":0,
    "nersc_ldms_dcgm_tensor_hmma_active":0,
    "nersc_ldms_dcgm_tensor_imma_active":0
  },
  {
    "index":56,
    "timestamp":1777506065000,
    "hostname":"nid002353",
    "gpu_id":2,
    "nersc_ldms_dcgm_dram_active":0.0000001366,
    "nersc_ldms_dcgm_fb_free":38747,
    "nersc_ldms_dcgm_fb_used":1694,
    "nersc_ldms_dcgm_fp16_active":0,
    "nersc_ldms_dcgm_fp32_active":0,
    "nersc_ldms_dcgm_fp64_active":0,
    "nersc_ldms_dcgm_gr_engine_active":0.0,
    "nersc_ldms_dcgm_sm_active":0,
    "nersc_ldms_dcgm_tensor_active":0,
    "nersc_ldms_dcgm_tensor_hmma_active":0,
    "nersc_ldms_dcgm_tensor_imma_active":0
  },
  {
    "index":57,
    "timestamp":1777506065000,
    "hostname":"nid002353",
    "gpu_id":3,
    "nersc_ldms_dcgm_dram_active":0.0000000856,
    "nersc_ldms_dcgm_fb_free":38747,
    "nersc_ldms_dcgm_fb_used":1694,
    "nersc_ldms_dcgm_fp16_active":0,
    "nersc_ldms_dcgm_fp32_active":0,
    "nersc_ldms_dcgm_fp64_active":0,
    "nersc_ldms_dcgm_gr_engine_active":0.0,
    "nersc_ldms_dcgm_sm_active":0,
    "nersc_ldms_dcgm_tensor_active":0,
    "nersc_ldms_dcgm_tensor_hmma_active":0,
    "nersc_ldms_dcgm_tensor_imma_active":0
  },
  {
    "index":58,
    "timestamp":1777506075000,
    "hostname":"nid002240",
    "gpu_id":0,
    "nersc_ldms_dcgm_dram_active":0.0000000067,
    "nersc_ldms_dcgm_fb_free":38747,
    "nersc_ldms_dcgm_fb_used":1694,
    "nersc_ldms_dcgm_fp16_active":0,
    "nersc_ldms_dcgm_fp32_active":0,
    "nersc_ldms_dcgm_fp64_active":0,
    "nersc_ldms_dcgm_gr_engine_active":0.0,
    "nersc_ldms_dcgm_sm_active":0,
    "nersc_ldms_dcgm_tensor_active":0,
    "nersc_ldms_dcgm_tensor_hmma_active":0,
    "nersc_ldms_dcgm_tensor_imma_active":0
  },
  {
    "index":59,
    "timestamp":1777506075000,
    "hostname":"nid002240",
    "gpu_id":1,
    "nersc_ldms_dcgm_dram_active":0.0000001228,
    "nersc_ldms_dcgm_fb_free":38747,
    "nersc_ldms_dcgm_fb_used":1694,
    "nersc_ldms_dcgm_fp16_active":0,
    "nersc_ldms_dcgm_fp32_active":0,
    "nersc_ldms_dcgm_fp64_active":0,
    "nersc_ldms_dcgm_gr_engine_active":0.0,
    "nersc_ldms_dcgm_sm_active":0,
    "nersc_ldms_dcgm_tensor_active":0,
    "nersc_ldms_dcgm_tensor_hmma_active":0,
    "nersc_ldms_dcgm_tensor_imma_active":0
  },
  {
    "index":60,
    "timestamp":1777506075000,
    "hostname":"nid002240",
    "gpu_id":2,
    "nersc_ldms_dcgm_dram_active":0.0000000564,
    "nersc_ldms_dcgm_fb_free":38747,
    "nersc_ldms_dcgm_fb_used":1694,
    "nersc_ldms_dcgm_fp16_active":0,
    "nersc_ldms_dcgm_fp32_active":0,
    "nersc_ldms_dcgm_fp64_active":0,
    "nersc_ldms_dcgm_gr_engine_active":0.0,
    "nersc_ldms_dcgm_sm_active":0,
    "nersc_ldms_dcgm_tensor_active":0,
    "nersc_ldms_dcgm_tensor_hmma_active":0,
    "nersc_ldms_dcgm_tensor_imma_active":0
  },
  {
    "index":61,
    "timestamp":1777506075000,
    "hostname":"nid002240",
    "gpu_id":3,
    "nersc_ldms_dcgm_dram_active":0.00000001,
    "nersc_ldms_dcgm_fb_free":38747,
    "nersc_ldms_dcgm_fb_used":1694,
    "nersc_ldms_dcgm_fp16_active":0,
    "nersc_ldms_dcgm_fp32_active":0,
    "nersc_ldms_dcgm_fp64_active":0,
    "nersc_ldms_dcgm_gr_engine_active":0.0,
    "nersc_ldms_dcgm_sm_active":0,
    "nersc_ldms_dcgm_tensor_active":0,
    "nersc_ldms_dcgm_tensor_hmma_active":0,
    "nersc_ldms_dcgm_tensor_imma_active":0
  },
  {
    "index":62,
    "timestamp":1777506075000,
    "hostname":"nid002353",
    "gpu_id":0,
    "nersc_ldms_dcgm_dram_active":0.0000001227,
    "nersc_ldms_dcgm_fb_free":38747,
    "nersc_ldms_dcgm_fb_used":1694,
    "nersc_ldms_dcgm_fp16_active":0,
    "nersc_ldms_dcgm_fp32_active":0,
    "nersc_ldms_dcgm_fp64_active":0,
    "nersc_ldms_dcgm_gr_engine_active":0.0,
    "nersc_ldms_dcgm_sm_active":0,
    "nersc_ldms_dcgm_tensor_active":0,
    "nersc_ldms_dcgm_tensor_hmma_active":0,
    "nersc_ldms_dcgm_tensor_imma_active":0
  },
  {
    "index":63,
    "timestamp":1777506075000,
    "hostname":"nid002353",
    "gpu_id":1,
    "nersc_ldms_dcgm_dram_active":0.0000000447,
    "nersc_ldms_dcgm_fb_free":38747,
    "nersc_ldms_dcgm_fb_used":1694,
    "nersc_ldms_dcgm_fp16_active":0,
    "nersc_ldms_dcgm_fp32_active":0,
    "nersc_ldms_dcgm_fp64_active":0,
    "nersc_ldms_dcgm_gr_engine_active":0.0,
    "nersc_ldms_dcgm_sm_active":0,
    "nersc_ldms_dcgm_tensor_active":0,
    "nersc_ldms_dcgm_tensor_hmma_active":0,
    "nersc_ldms_dcgm_tensor_imma_active":0
  },
  {
    "index":64,
    "timestamp":1777506075000,
    "hostname":"nid002353",
    "gpu_id":2,
    "nersc_ldms_dcgm_dram_active":0.0000001272,
    "nersc_ldms_dcgm_fb_free":38747,
    "nersc_ldms_dcgm_fb_used":1694,
    "nersc_ldms_dcgm_fp16_active":0,
    "nersc_ldms_dcgm_fp32_active":0,
    "nersc_ldms_dcgm_fp64_active":0,
    "nersc_ldms_dcgm_gr_engine_active":0.0,
    "nersc_ldms_dcgm_sm_active":0,
    "nersc_ldms_dcgm_tensor_active":0,
    "nersc_ldms_dcgm_tensor_hmma_active":0,
    "nersc_ldms_dcgm_tensor_imma_active":0
  },
  {
    "index":65,
    "timestamp":1777506075000,
    "hostname":"nid002353",
    "gpu_id":3,
    "nersc_ldms_dcgm_dram_active":0.0000000838,
    "nersc_ldms_dcgm_fb_free":38747,
    "nersc_ldms_dcgm_fb_used":1694,
    "nersc_ldms_dcgm_fp16_active":0,
    "nersc_ldms_dcgm_fp32_active":0,
    "nersc_ldms_dcgm_fp64_active":0,
    "nersc_ldms_dcgm_gr_engine_active":0.0,
    "nersc_ldms_dcgm_sm_active":0,
    "nersc_ldms_dcgm_tensor_active":0,
    "nersc_ldms_dcgm_tensor_hmma_active":0,
    "nersc_ldms_dcgm_tensor_imma_active":0
  },
  {
    "index":66,
    "timestamp":1777506085000,
    "hostname":"nid002240",
    "gpu_id":0,
    "nersc_ldms_dcgm_dram_active":0.0000000081,
    "nersc_ldms_dcgm_fb_free":38747,
    "nersc_ldms_dcgm_fb_used":1694,
    "nersc_ldms_dcgm_fp16_active":0,
    "nersc_ldms_dcgm_fp32_active":0,
    "nersc_ldms_dcgm_fp64_active":0,
    "nersc_ldms_dcgm_gr_engine_active":0.0,
    "nersc_ldms_dcgm_sm_active":0,
    "nersc_ldms_dcgm_tensor_active":0,
    "nersc_ldms_dcgm_tensor_hmma_active":0,
    "nersc_ldms_dcgm_tensor_imma_active":0
  },
  {
    "index":67,
    "timestamp":1777506085000,
    "hostname":"nid002240",
    "gpu_id":1,
    "nersc_ldms_dcgm_dram_active":0.0000001222,
    "nersc_ldms_dcgm_fb_free":38747,
    "nersc_ldms_dcgm_fb_used":1694,
    "nersc_ldms_dcgm_fp16_active":0,
    "nersc_ldms_dcgm_fp32_active":0,
    "nersc_ldms_dcgm_fp64_active":0,
    "nersc_ldms_dcgm_gr_engine_active":0.0,
    "nersc_ldms_dcgm_sm_active":0,
    "nersc_ldms_dcgm_tensor_active":0,
    "nersc_ldms_dcgm_tensor_hmma_active":0,
    "nersc_ldms_dcgm_tensor_imma_active":0
  },
  {
    "index":68,
    "timestamp":1777506085000,
    "hostname":"nid002240",
    "gpu_id":2,
    "nersc_ldms_dcgm_dram_active":0.0000000597,
    "nersc_ldms_dcgm_fb_free":38747,
    "nersc_ldms_dcgm_fb_used":1694,
    "nersc_ldms_dcgm_fp16_active":0,
    "nersc_ldms_dcgm_fp32_active":0,
    "nersc_ldms_dcgm_fp64_active":0,
    "nersc_ldms_dcgm_gr_engine_active":0.0,
    "nersc_ldms_dcgm_sm_active":0,
    "nersc_ldms_dcgm_tensor_active":0,
    "nersc_ldms_dcgm_tensor_hmma_active":0,
    "nersc_ldms_dcgm_tensor_imma_active":0
  },
  {
    "index":69,
    "timestamp":1777506085000,
    "hostname":"nid002240",
    "gpu_id":3,
    "nersc_ldms_dcgm_dram_active":0.0000000096,
    "nersc_ldms_dcgm_fb_free":38747,
    "nersc_ldms_dcgm_fb_used":1694,
    "nersc_ldms_dcgm_fp16_active":0,
    "nersc_ldms_dcgm_fp32_active":0,
    "nersc_ldms_dcgm_fp64_active":0,
    "nersc_ldms_dcgm_gr_engine_active":0.0,
    "nersc_ldms_dcgm_sm_active":0,
    "nersc_ldms_dcgm_tensor_active":0,
    "nersc_ldms_dcgm_tensor_hmma_active":0,
    "nersc_ldms_dcgm_tensor_imma_active":0
  },
  {
    "index":70,
    "timestamp":1777506085000,
    "hostname":"nid002353",
    "gpu_id":0,
    "nersc_ldms_dcgm_dram_active":0.0000001106,
    "nersc_ldms_dcgm_fb_free":38747,
    "nersc_ldms_dcgm_fb_used":1694,
    "nersc_ldms_dcgm_fp16_active":0,
    "nersc_ldms_dcgm_fp32_active":0,
    "nersc_ldms_dcgm_fp64_active":0,
    "nersc_ldms_dcgm_gr_engine_active":0.0,
    "nersc_ldms_dcgm_sm_active":0,
    "nersc_ldms_dcgm_tensor_active":0,
    "nersc_ldms_dcgm_tensor_hmma_active":0,
    "nersc_ldms_dcgm_tensor_imma_active":0
  },
  {
    "index":71,
    "timestamp":1777506085000,
    "hostname":"nid002353",
    "gpu_id":1,
    "nersc_ldms_dcgm_dram_active":0.000000044,
    "nersc_ldms_dcgm_fb_free":38747,
    "nersc_ldms_dcgm_fb_used":1694,
    "nersc_ldms_dcgm_fp16_active":0,
    "nersc_ldms_dcgm_fp32_active":0,
    "nersc_ldms_dcgm_fp64_active":0,
    "nersc_ldms_dcgm_gr_engine_active":0.0,
    "nersc_ldms_dcgm_sm_active":0,
    "nersc_ldms_dcgm_tensor_active":0,
    "nersc_ldms_dcgm_tensor_hmma_active":0,
    "nersc_ldms_dcgm_tensor_imma_active":0
  },
  {
    "index":72,
    "timestamp":1777506085000,
    "hostname":"nid002353",
    "gpu_id":2,
    "nersc_ldms_dcgm_dram_active":0.0000001384,
    "nersc_ldms_dcgm_fb_free":38747,
    "nersc_ldms_dcgm_fb_used":1694,
    "nersc_ldms_dcgm_fp16_active":0,
    "nersc_ldms_dcgm_fp32_active":0,
    "nersc_ldms_dcgm_fp64_active":0,
    "nersc_ldms_dcgm_gr_engine_active":0.0,
    "nersc_ldms_dcgm_sm_active":0,
    "nersc_ldms_dcgm_tensor_active":0,
    "nersc_ldms_dcgm_tensor_hmma_active":0,
    "nersc_ldms_dcgm_tensor_imma_active":0
  },
  {
    "index":73,
    "timestamp":1777506085000,
    "hostname":"nid002353",
    "gpu_id":3,
    "nersc_ldms_dcgm_dram_active":0.0000000889,
    "nersc_ldms_dcgm_fb_free":38747,
    "nersc_ldms_dcgm_fb_used":1694,
    "nersc_ldms_dcgm_fp16_active":0,
    "nersc_ldms_dcgm_fp32_active":0,
    "nersc_ldms_dcgm_fp64_active":0,
    "nersc_ldms_dcgm_gr_engine_active":0.0,
    "nersc_ldms_dcgm_sm_active":0,
    "nersc_ldms_dcgm_tensor_active":0,
    "nersc_ldms_dcgm_tensor_hmma_active":0,
    "nersc_ldms_dcgm_tensor_imma_active":0
  },
  {
    "index":74,
    "timestamp":1777506095000,
    "hostname":"nid002240",
    "gpu_id":0,
    "nersc_ldms_dcgm_dram_active":0.0000000079,
    "nersc_ldms_dcgm_fb_free":38747,
    "nersc_ldms_dcgm_fb_used":1694,
    "nersc_ldms_dcgm_fp16_active":0,
    "nersc_ldms_dcgm_fp32_active":0,
    "nersc_ldms_dcgm_fp64_active":0,
    "nersc_ldms_dcgm_gr_engine_active":0.0,
    "nersc_ldms_dcgm_sm_active":0,
    "nersc_ldms_dcgm_tensor_active":0,
    "nersc_ldms_dcgm_tensor_hmma_active":0,
    "nersc_ldms_dcgm_tensor_imma_active":0
  },
  {
    "index":75,
    "timestamp":1777506095000,
    "hostname":"nid002240",
    "gpu_id":1,
    "nersc_ldms_dcgm_dram_active":0.00000013,
    "nersc_ldms_dcgm_fb_free":38747,
    "nersc_ldms_dcgm_fb_used":1694,
    "nersc_ldms_dcgm_fp16_active":0,
    "nersc_ldms_dcgm_fp32_active":0,
    "nersc_ldms_dcgm_fp64_active":0,
    "nersc_ldms_dcgm_gr_engine_active":0.0,
    "nersc_ldms_dcgm_sm_active":0,
    "nersc_ldms_dcgm_tensor_active":0,
    "nersc_ldms_dcgm_tensor_hmma_active":0,
    "nersc_ldms_dcgm_tensor_imma_active":0
  },
  {
    "index":76,
    "timestamp":1777506095000,
    "hostname":"nid002240",
    "gpu_id":2,
    "nersc_ldms_dcgm_dram_active":0.0000000614,
    "nersc_ldms_dcgm_fb_free":38747,
    "nersc_ldms_dcgm_fb_used":1694,
    "nersc_ldms_dcgm_fp16_active":0,
    "nersc_ldms_dcgm_fp32_active":0,
    "nersc_ldms_dcgm_fp64_active":0,
    "nersc_ldms_dcgm_gr_engine_active":0.0,
    "nersc_ldms_dcgm_sm_active":0,
    "nersc_ldms_dcgm_tensor_active":0,
    "nersc_ldms_dcgm_tensor_hmma_active":0,
    "nersc_ldms_dcgm_tensor_imma_active":0
  },
  {
    "index":77,
    "timestamp":1777506095000,
    "hostname":"nid002240",
    "gpu_id":3,
    "nersc_ldms_dcgm_dram_active":0.000000011,
    "nersc_ldms_dcgm_fb_free":38747,
    "nersc_ldms_dcgm_fb_used":1694,
    "nersc_ldms_dcgm_fp16_active":0,
    "nersc_ldms_dcgm_fp32_active":0,
    "nersc_ldms_dcgm_fp64_active":0,
    "nersc_ldms_dcgm_gr_engine_active":0.0,
    "nersc_ldms_dcgm_sm_active":0,
    "nersc_ldms_dcgm_tensor_active":0,
    "nersc_ldms_dcgm_tensor_hmma_active":0,
    "nersc_ldms_dcgm_tensor_imma_active":0
  },
  {
    "index":78,
    "timestamp":1777506095000,
    "hostname":"nid002353",
    "gpu_id":0,
    "nersc_ldms_dcgm_dram_active":0.0000001218,
    "nersc_ldms_dcgm_fb_free":38747,
    "nersc_ldms_dcgm_fb_used":1694,
    "nersc_ldms_dcgm_fp16_active":0,
    "nersc_ldms_dcgm_fp32_active":0,
    "nersc_ldms_dcgm_fp64_active":0,
    "nersc_ldms_dcgm_gr_engine_active":0.0,
    "nersc_ldms_dcgm_sm_active":0,
    "nersc_ldms_dcgm_tensor_active":0,
    "nersc_ldms_dcgm_tensor_hmma_active":0,
    "nersc_ldms_dcgm_tensor_imma_active":0
  },
  {
    "index":79,
    "timestamp":1777506095000,
    "hostname":"nid002353",
    "gpu_id":1,
    "nersc_ldms_dcgm_dram_active":0.0000000471,
    "nersc_ldms_dcgm_fb_free":38747,
    "nersc_ldms_dcgm_fb_used":1694,
    "nersc_ldms_dcgm_fp16_active":0,
    "nersc_ldms_dcgm_fp32_active":0,
    "nersc_ldms_dcgm_fp64_active":0,
    "nersc_ldms_dcgm_gr_engine_active":0.0,
    "nersc_ldms_dcgm_sm_active":0,
    "nersc_ldms_dcgm_tensor_active":0,
    "nersc_ldms_dcgm_tensor_hmma_active":0,
    "nersc_ldms_dcgm_tensor_imma_active":0
  },
  {
    "index":80,
    "timestamp":1777506095000,
    "hostname":"nid002353",
    "gpu_id":2,
    "nersc_ldms_dcgm_dram_active":0.0000000981,
    "nersc_ldms_dcgm_fb_free":38747,
    "nersc_ldms_dcgm_fb_used":1694,
    "nersc_ldms_dcgm_fp16_active":0,
    "nersc_ldms_dcgm_fp32_active":0,
    "nersc_ldms_dcgm_fp64_active":0,
    "nersc_ldms_dcgm_gr_engine_active":0.0,
    "nersc_ldms_dcgm_sm_active":0,
    "nersc_ldms_dcgm_tensor_active":0,
    "nersc_ldms_dcgm_tensor_hmma_active":0,
    "nersc_ldms_dcgm_tensor_imma_active":0
  },
  {
    "index":81,
    "timestamp":1777506095000,
    "hostname":"nid002353",
    "gpu_id":3,
    "nersc_ldms_dcgm_dram_active":0.0000000702,
    "nersc_ldms_dcgm_fb_free":38747,
    "nersc_ldms_dcgm_fb_used":1694,
    "nersc_ldms_dcgm_fp16_active":0,
    "nersc_ldms_dcgm_fp32_active":0,
    "nersc_ldms_dcgm_fp64_active":0,
    "nersc_ldms_dcgm_gr_engine_active":0.0,
    "nersc_ldms_dcgm_sm_active":0,
    "nersc_ldms_dcgm_tensor_active":0,
    "nersc_ldms_dcgm_tensor_hmma_active":0,
    "nersc_ldms_dcgm_tensor_imma_active":0
  },
  {
    "index":82,
    "timestamp":1777506105000,
    "hostname":"nid002240",
    "gpu_id":0,
    "nersc_ldms_dcgm_dram_active":0.0000000074,
    "nersc_ldms_dcgm_fb_free":38747,
    "nersc_ldms_dcgm_fb_used":1694,
    "nersc_ldms_dcgm_fp16_active":0,
    "nersc_ldms_dcgm_fp32_active":0,
    "nersc_ldms_dcgm_fp64_active":0,
    "nersc_ldms_dcgm_gr_engine_active":0.0,
    "nersc_ldms_dcgm_sm_active":0,
    "nersc_ldms_dcgm_tensor_active":0,
    "nersc_ldms_dcgm_tensor_hmma_active":0,
    "nersc_ldms_dcgm_tensor_imma_active":0
  },
  {
    "index":83,
    "timestamp":1777506105000,
    "hostname":"nid002240",
    "gpu_id":1,
    "nersc_ldms_dcgm_dram_active":0.0000001249,
    "nersc_ldms_dcgm_fb_free":38747,
    "nersc_ldms_dcgm_fb_used":1694,
    "nersc_ldms_dcgm_fp16_active":0,
    "nersc_ldms_dcgm_fp32_active":0,
    "nersc_ldms_dcgm_fp64_active":0,
    "nersc_ldms_dcgm_gr_engine_active":0.0,
    "nersc_ldms_dcgm_sm_active":0,
    "nersc_ldms_dcgm_tensor_active":0,
    "nersc_ldms_dcgm_tensor_hmma_active":0,
    "nersc_ldms_dcgm_tensor_imma_active":0
  },
  {
    "index":84,
    "timestamp":1777506105000,
    "hostname":"nid002240",
    "gpu_id":2,
    "nersc_ldms_dcgm_dram_active":0.0000000595,
    "nersc_ldms_dcgm_fb_free":38747,
    "nersc_ldms_dcgm_fb_used":1694,
    "nersc_ldms_dcgm_fp16_active":0,
    "nersc_ldms_dcgm_fp32_active":0,
    "nersc_ldms_dcgm_fp64_active":0,
    "nersc_ldms_dcgm_gr_engine_active":0.0,
    "nersc_ldms_dcgm_sm_active":0,
    "nersc_ldms_dcgm_tensor_active":0,
    "nersc_ldms_dcgm_tensor_hmma_active":0,
    "nersc_ldms_dcgm_tensor_imma_active":0
  },
  {
    "index":85,
    "timestamp":1777506105000,
    "hostname":"nid002240",
    "gpu_id":3,
    "nersc_ldms_dcgm_dram_active":0.0000000107,
    "nersc_ldms_dcgm_fb_free":38747,
    "nersc_ldms_dcgm_fb_used":1694,
    "nersc_ldms_dcgm_fp16_active":0,
    "nersc_ldms_dcgm_fp32_active":0,
    "nersc_ldms_dcgm_fp64_active":0,
    "nersc_ldms_dcgm_gr_engine_active":0.0,
    "nersc_ldms_dcgm_sm_active":0,
    "nersc_ldms_dcgm_tensor_active":0,
    "nersc_ldms_dcgm_tensor_hmma_active":0,
    "nersc_ldms_dcgm_tensor_imma_active":0
  },
  {
    "index":86,
    "timestamp":1777506105000,
    "hostname":"nid002353",
    "gpu_id":0,
    "nersc_ldms_dcgm_dram_active":0.0000001218,
    "nersc_ldms_dcgm_fb_free":38747,
    "nersc_ldms_dcgm_fb_used":1694,
    "nersc_ldms_dcgm_fp16_active":0,
    "nersc_ldms_dcgm_fp32_active":0,
    "nersc_ldms_dcgm_fp64_active":0,
    "nersc_ldms_dcgm_gr_engine_active":0.0,
    "nersc_ldms_dcgm_sm_active":0,
    "nersc_ldms_dcgm_tensor_active":0,
    "nersc_ldms_dcgm_tensor_hmma_active":0,
    "nersc_ldms_dcgm_tensor_imma_active":0
  },
  {
    "index":87,
    "timestamp":1777506105000,
    "hostname":"nid002353",
    "gpu_id":1,
    "nersc_ldms_dcgm_dram_active":0.0000000388,
    "nersc_ldms_dcgm_fb_free":38747,
    "nersc_ldms_dcgm_fb_used":1694,
    "nersc_ldms_dcgm_fp16_active":0,
    "nersc_ldms_dcgm_fp32_active":0,
    "nersc_ldms_dcgm_fp64_active":0,
    "nersc_ldms_dcgm_gr_engine_active":0.0,
    "nersc_ldms_dcgm_sm_active":0,
    "nersc_ldms_dcgm_tensor_active":0,
    "nersc_ldms_dcgm_tensor_hmma_active":0,
    "nersc_ldms_dcgm_tensor_imma_active":0
  },
  {
    "index":88,
    "timestamp":1777506105000,
    "hostname":"nid002353",
    "gpu_id":2,
    "nersc_ldms_dcgm_dram_active":0.0000001238,
    "nersc_ldms_dcgm_fb_free":38747,
    "nersc_ldms_dcgm_fb_used":1694,
    "nersc_ldms_dcgm_fp16_active":0,
    "nersc_ldms_dcgm_fp32_active":0,
    "nersc_ldms_dcgm_fp64_active":0,
    "nersc_ldms_dcgm_gr_engine_active":0.0,
    "nersc_ldms_dcgm_sm_active":0,
    "nersc_ldms_dcgm_tensor_active":0,
    "nersc_ldms_dcgm_tensor_hmma_active":0,
    "nersc_ldms_dcgm_tensor_imma_active":0
  },
  {
    "index":89,
    "timestamp":1777506105000,
    "hostname":"nid002353",
    "gpu_id":3,
    "nersc_ldms_dcgm_dram_active":0.0000000853,
    "nersc_ldms_dcgm_fb_free":38747,
    "nersc_ldms_dcgm_fb_used":1694,
    "nersc_ldms_dcgm_fp16_active":0,
    "nersc_ldms_dcgm_fp32_active":0,
    "nersc_ldms_dcgm_fp64_active":0,
    "nersc_ldms_dcgm_gr_engine_active":0.0,
    "nersc_ldms_dcgm_sm_active":0,
    "nersc_ldms_dcgm_tensor_active":0,
    "nersc_ldms_dcgm_tensor_hmma_active":0,
    "nersc_ldms_dcgm_tensor_imma_active":0
  },
  {
    "index":90,
    "timestamp":1777506115000,
    "hostname":"nid002240",
    "gpu_id":0,
    "nersc_ldms_dcgm_dram_active":0.0000000077,
    "nersc_ldms_dcgm_fb_free":38747,
    "nersc_ldms_dcgm_fb_used":1694,
    "nersc_ldms_dcgm_fp16_active":0,
    "nersc_ldms_dcgm_fp32_active":0,
    "nersc_ldms_dcgm_fp64_active":0,
    "nersc_ldms_dcgm_gr_engine_active":0.0,
    "nersc_ldms_dcgm_sm_active":0,
    "nersc_ldms_dcgm_tensor_active":0,
    "nersc_ldms_dcgm_tensor_hmma_active":0,
    "nersc_ldms_dcgm_tensor_imma_active":0
  },
  {
    "index":91,
    "timestamp":1777506115000,
    "hostname":"nid002240",
    "gpu_id":1,
    "nersc_ldms_dcgm_dram_active":0.0000001074,
    "nersc_ldms_dcgm_fb_free":38747,
    "nersc_ldms_dcgm_fb_used":1694,
    "nersc_ldms_dcgm_fp16_active":0,
    "nersc_ldms_dcgm_fp32_active":0,
    "nersc_ldms_dcgm_fp64_active":0,
    "nersc_ldms_dcgm_gr_engine_active":0.0,
    "nersc_ldms_dcgm_sm_active":0,
    "nersc_ldms_dcgm_tensor_active":0,
    "nersc_ldms_dcgm_tensor_hmma_active":0,
    "nersc_ldms_dcgm_tensor_imma_active":0
  },
  {
    "index":92,
    "timestamp":1777506115000,
    "hostname":"nid002240",
    "gpu_id":2,
    "nersc_ldms_dcgm_dram_active":0.0000000575,
    "nersc_ldms_dcgm_fb_free":38747,
    "nersc_ldms_dcgm_fb_used":1694,
    "nersc_ldms_dcgm_fp16_active":0,
    "nersc_ldms_dcgm_fp32_active":0,
    "nersc_ldms_dcgm_fp64_active":0,
    "nersc_ldms_dcgm_gr_engine_active":0.0,
    "nersc_ldms_dcgm_sm_active":0,
    "nersc_ldms_dcgm_tensor_active":0,
    "nersc_ldms_dcgm_tensor_hmma_active":0,
    "nersc_ldms_dcgm_tensor_imma_active":0
  },
  {
    "index":93,
    "timestamp":1777506115000,
    "hostname":"nid002240",
    "gpu_id":3,
    "nersc_ldms_dcgm_dram_active":0.0000000103,
    "nersc_ldms_dcgm_fb_free":38747,
    "nersc_ldms_dcgm_fb_used":1694,
    "nersc_ldms_dcgm_fp16_active":0,
    "nersc_ldms_dcgm_fp32_active":0,
    "nersc_ldms_dcgm_fp64_active":0,
    "nersc_ldms_dcgm_gr_engine_active":0.0,
    "nersc_ldms_dcgm_sm_active":0,
    "nersc_ldms_dcgm_tensor_active":0,
    "nersc_ldms_dcgm_tensor_hmma_active":0,
    "nersc_ldms_dcgm_tensor_imma_active":0
  },
  {
    "index":94,
    "timestamp":1777506115000,
    "hostname":"nid002353",
    "gpu_id":0,
    "nersc_ldms_dcgm_dram_active":0.0000001101,
    "nersc_ldms_dcgm_fb_free":38747,
    "nersc_ldms_dcgm_fb_used":1694,
    "nersc_ldms_dcgm_fp16_active":0,
    "nersc_ldms_dcgm_fp32_active":0,
    "nersc_ldms_dcgm_fp64_active":0,
    "nersc_ldms_dcgm_gr_engine_active":0.0,
    "nersc_ldms_dcgm_sm_active":0,
    "nersc_ldms_dcgm_tensor_active":0,
    "nersc_ldms_dcgm_tensor_hmma_active":0,
    "nersc_ldms_dcgm_tensor_imma_active":0
  },
  {
    "index":95,
    "timestamp":1777506115000,
    "hostname":"nid002353",
    "gpu_id":1,
    "nersc_ldms_dcgm_dram_active":0.0000000396,
    "nersc_ldms_dcgm_fb_free":38747,
    "nersc_ldms_dcgm_fb_used":1694,
    "nersc_ldms_dcgm_fp16_active":0,
    "nersc_ldms_dcgm_fp32_active":0,
    "nersc_ldms_dcgm_fp64_active":0,
    "nersc_ldms_dcgm_gr_engine_active":0.0,
    "nersc_ldms_dcgm_sm_active":0,
    "nersc_ldms_dcgm_tensor_active":0,
    "nersc_ldms_dcgm_tensor_hmma_active":0,
    "nersc_ldms_dcgm_tensor_imma_active":0
  },
  {
    "index":96,
    "timestamp":1777506115000,
    "hostname":"nid002353",
    "gpu_id":2,
    "nersc_ldms_dcgm_dram_active":0.0000001291,
    "nersc_ldms_dcgm_fb_free":38747,
    "nersc_ldms_dcgm_fb_used":1694,
    "nersc_ldms_dcgm_fp16_active":0,
    "nersc_ldms_dcgm_fp32_active":0,
    "nersc_ldms_dcgm_fp64_active":0,
    "nersc_ldms_dcgm_gr_engine_active":0.0,
    "nersc_ldms_dcgm_sm_active":0,
    "nersc_ldms_dcgm_tensor_active":0,
    "nersc_ldms_dcgm_tensor_hmma_active":0,
    "nersc_ldms_dcgm_tensor_imma_active":0
  },
  {
    "index":97,
    "timestamp":1777506115000,
    "hostname":"nid002353",
    "gpu_id":3,
    "nersc_ldms_dcgm_dram_active":0.0000000968,
    "nersc_ldms_dcgm_fb_free":38747,
    "nersc_ldms_dcgm_fb_used":1694,
    "nersc_ldms_dcgm_fp16_active":0,
    "nersc_ldms_dcgm_fp32_active":0,
    "nersc_ldms_dcgm_fp64_active":0,
    "nersc_ldms_dcgm_gr_engine_active":0.0,
    "nersc_ldms_dcgm_sm_active":0,
    "nersc_ldms_dcgm_tensor_active":0,
    "nersc_ldms_dcgm_tensor_hmma_active":0,
    "nersc_ldms_dcgm_tensor_imma_active":0
  }
]